column_cleaner.py
column_cleaner-0.0.2.dist-info/LICENSE.txt
column_cleaner-0.0.2.dist-info/METADATA
column_cleaner-0.0.2.dist-info/WHEEL
column_cleaner-0.0.2.dist-info/top_level.txt
column_cleaner-0.0.2.dist-info/RECORD
