Metadata-Version: 2.1
Name: column-cleaner
Version: 0.0.2
Summary: A column cleaner, which will clean the numerical values and spaces
Home-page: UNKNOWN
Author: KIE Square Analytics
License: UNKNOWN
Keywords: column cleaner,number cleaner,space cleaner
Platform: UNKNOWN
Classifier: Programming Language :: Python :: 3
Classifier: License :: OSI Approved :: MIT License
Classifier: Operating System :: OS Independent
Requires-Python: >=3.6
License-File: LICENSE.txt
Requires-Dist: pandas
